{
  "_class": "group",
  "do_objectID": "5EA7AF9B-215B-4088-9A4E-8A85DF395463",
  "exportOptions": {
    "_class": "exportOptions",
    "exportFormats": [
    ],
    "includedLayerIds": [
    ],
    "layerOptions": 0,
    "shouldTrim": false
  },
  "frame": {
    "_class": "rect",
    "constrainProportions": false,
    "height": 4,
    "width": 200,
    "x": 0,
    "y": 44
  },
  "hasClickThrough": false,
  "isFlippedHorizontal": false,
  "isFlippedVertical": false,
  "isLocked": false,
  "isVisible": true,
  "layerListExpandedType": 2,
  "layers": [
    {
      "class": "shapeGroup",
      "id": "BD23B99F-C8B9-4503-A9F2-E31E439E9010"
    },
    {
      "class": "symbolInstance",
      "id": "3F2219E0-B892-43C5-A13D-2D4E8FDD169C"
    }
  ],
  "name": "Rectangle 4",
  "nameIsFixed": false,
  "resizingConstraint": 39,
  "resizingType": 0,
  "rotation": 0,
  "shouldBreakMaskChain": false,
  "style": {
    "_class": "style",
    "endDecorationType": 0,
    "miterLimit": 10,
    "startDecorationType": 0
  },
  "userInfo": {
    "com.animaapp.stc-sketch-plugin": {
      "kModelPropertiesKey": {
      }
    }
  }
}