{
  "_class": "group",
  "do_objectID": "2C0B21F0-49C6-487B-81FA-072AB4DE3BC9",
  "exportOptions": {
    "_class": "exportOptions",
    "exportFormats": [
    ],
    "includedLayerIds": [
    ],
    "layerOptions": 0,
    "shouldTrim": false
  },
  "frame": {
    "_class": "rect",
    "constrainProportions": false,
    "height": 32,
    "width": 200,
    "x": 0,
    "y": 0
  },
  "hasClickThrough": false,
  "isFlippedHorizontal": false,
  "isFlippedVertical": false,
  "isLocked": false,
  "isVisible": true,
  "layerListExpandedType": 2,
  "layers": [
    {
      "class": "shapeGroup",
      "id": "31606FD1-67CA-4D57-9FA2-67697841E526"
    },
    {
      "class": "symbolInstance",
      "id": "A7A51EFC-A99D-43E7-9D2C-48395B5FB132"
    }
  ],
  "name": "Rectangle 4",
  "nameIsFixed": false,
  "resizingConstraint": 15,
  "resizingType": 0,
  "rotation": 0,
  "shouldBreakMaskChain": false,
  "style": {
    "_class": "style",
    "endDecorationType": 0,
    "miterLimit": 10,
    "startDecorationType": 0
  },
  "userInfo": {
    "com.animaapp.stc-sketch-plugin": {
      "kModelPropertiesKey": {
      }
    }
  }
}